slack/__init__.py
slack/actions.py
slack/commands.py
slack/events.py
slack/exceptions.py
slack/io/__init__.py
slack/io/abc.py
slack/io/aiohttp.py
slack/io/curio.py
slack/io/requests.py
slack/io/trio.py
slack/methods.py
slack/py.typed
slack/sansio.py
slack/tests/__init__.py
slack/tests/conftest.py
slack/tests/data/__init__.py
slack/tests/data/actions.py
slack/tests/data/commands.py
slack/tests/data/events.py
slack/tests/data/methods.py
slack/tests/plugin.py
slack/tests/test.sh
slack/tests/test_actions.py
slack/tests/test_commands.py
slack/tests/test_events.py
slack/tests/test_examples.py
slack/tests/test_io.py
slack/tests/test_sansio.py
slack_sansio-1.1.0.dist-info/LICENSE
slack_sansio-1.1.0.dist-info/WHEEL
slack_sansio-1.1.0.dist-info/METADATA
slack_sansio-1.1.0.dist-info/RECORD
